Metadata-Version: 1.0
Name: film-director-genre
Version: 1
Summary: This package analyzes data of films and directors
Home-page: UNKNOWN
Author: Sydorenko Valeriia
Author-email: UNKNOWN
License: MIT
Platform: UNKNOWN
